pv_evaluation/__init__.py
pv_evaluation/benchmark/__init__.py
pv_evaluation/benchmark/data.py
pv_evaluation/benchmark/report.py
pv_evaluation/data/__init__.py
pv_evaluation/data/assignee/__init__.py
pv_evaluation/data/assignee/air-umass-assignees-benchmark.csv
pv_evaluation/data/assignee/nber-subset-assignees-benchmark.csv
pv_evaluation/data/inventor/__init__.py
pv_evaluation/data/inventor/als-inventors.csv
pv_evaluation/data/inventor/binette-2022-inventors-benchmark.csv
pv_evaluation/data/inventor/ens-inventors.csv
pv_evaluation/data/inventor/israeli-inventors-benchmark.csv
pv_evaluation/data/inventor/lai-2011-benchmark.csv
pv_evaluation/data/inventor/patentsview-inventors-benchmark.csv
pv_evaluation/templates/__init__.py
pv_evaluation/templates/render.py
pv_evaluation/templates/inventor/0-report.qmd
pv_evaluation/templates/inventor/1-header.qmd
pv_evaluation/templates/inventor/2-summary.qmd
pv_evaluation/templates/inventor/3-benchmark.qmd
pv_evaluation/templates/inventor/__init__.py
pv_evaluation/templates/inventor/footer.html
pv_evaluation/templates/inventor/header.html
pv_evaluation/templates/inventor/callouts/__init__.py
pv_evaluation/templates/inventor/callouts/between-cluster-tips.qmd
pv_evaluation/templates/inventor/callouts/cluster-errors-tips.qmd
pv_evaluation/templates/inventor/callouts/cluster-homogeneity-tips.qmd
pv_evaluation/templates/inventor/callouts/cluster-sizes-tips.qmd
pv_evaluation/templates/inventor/callouts/entropy-tips.qmd
pv_evaluation/templates/inventor/callouts/metrics-tips.qmd
pv_evaluation/templates/inventor/callouts/top-inventors-tips.qmd
pv_evaluation-2.1.1.data/scripts/process-inventors-hand-disambiguation.py
pv_evaluation-2.1.1.dist-info/LICENSE.txt
pv_evaluation-2.1.1.dist-info/METADATA
pv_evaluation-2.1.1.dist-info/WHEEL
pv_evaluation-2.1.1.dist-info/top_level.txt
pv_evaluation-2.1.1.dist-info/RECORD
