Metadata-Version: 2.1
Name: pv-evaluation
Version: 2.1.1
Summary: Tools to evaluate PatentsView's disambiguation algorithms
Home-page: https://github.com/OlivierBinette/PatentsView-Evaluation
Author: Olivier Binette, Sarvo Madhavan
Author-email: olivier.binette@gmail.com
License-File: LICENSE.txt
Requires-Dist: pandas
Requires-Dist: dask
Requires-Dist: matplotlib
Requires-Dist: pyarrow
Requires-Dist: python-snappy
Requires-Dist: numpy
Requires-Dist: plotly
Requires-Dist: scikit-learn
Requires-Dist: scipy
Requires-Dist: quarto
Requires-Dist: jinja2
Requires-Dist: kaleido
Requires-Dist: openpyxl
Requires-Dist: er-evaluation (>=2.0.0)
